[{".id":"*1","bypassed":"true","comment":"FreeKiosk Monitor - PS Station","disabled":"false","mac-address":"D4:AB:CD:7D:F8:7B","type":"bypassed"},{".id":"*2","bypassed":"true","comment":"TCL Monitor - PS Station","disabled":"false","mac-address":"D4:AB:CD:7D:F7:17","type":"bypassed"},{".id":"*3","address":"10.10.10.174","bypassed":"true","comment":"Monitor 10.10.10.174","disabled":"false","type":"bypassed"},{".id":"*4","address":"10.10.10.171","bypassed":"true","comment":"Monitor 10.10.10.171","disabled":"false","type":"bypassed"},{".id":"*5","address":"10.10.10.170","bypassed":"true","comment":"Monitor 10.10.10.170","disabled":"false","type":"bypassed"},{".id":"*6","address":"10.10.10.169","bypassed":"true","comment":"Monitor 10.10.10.169","disabled":"false","type":"bypassed"},{".id":"*D","bypassed":"true","comment":"ps-bypass:ps-01","disabled":"false","mac-address":"E8:D8:19:AD:DC:81","type":"bypassed"},{".id":"*E","bypassed":"true","comment":"ps-bypass:ps-02","disabled":"false","mac-address":"E8:D8:19:AB:4F:53","type":"bypassed"},{".id":"*F","bypassed":"true","comment":"ps-bypass:ps-03","disabled":"false","mac-address":"E8:61:7E:61:43:73","type":"bypassed"},{".id":"*10","bypassed":"true","comment":"ps-bypass:ps-04","disabled":"false","mac-address":"E8:D8:19:C1:AF:87","type":"bypassed"},{".id":"*11","bypassed":"true","comment":"ps-bypass:ps-05","disabled":"false","mac-address":"E8:61:7E:76:40:FB","type":"bypassed"},{".id":"*12","bypassed":"true","comment":"ps-bypass:ps-06","disabled":"false","mac-address":"2C:DC:D7:20:90:97","type":"bypassed"},{".id":"*13","bypassed":"true","comment":"ps-bypass:ps-07","disabled":"false","mac-address":"A4:FC:77:A1:20:91","type":"bypassed"},{".id":"*14","bypassed":"true","comment":"ps-bypass:ps-08","disabled":"false","mac-address":"E8:D8:19:BE:8C:3F","type":"bypassed"}]